<?xml version="1.0" encoding="utf-8"?>
<openerp>
    <data>
        <record id="project_task_percentage_form_inherit1" model="ir.ui.view">
            <field name="name">Project percentage</field>
            <field name="model">project.task</field>
            <field name="inherit_id" ref="project.view_task_form2"/>
            <field name="arch" type="xml">
                <field name="user_id" position="after">
                    <field name="porcentaje" />
                </field>
            </field>
        </record> 
    </data>
</openerp>        